niyofetch/__init__.py
niyofetch/__main__.py
niyofetch/neofetch
niyofetch/niyofetch.py
niyofetch-1.0.0.dist-info/LICENSE.md
niyofetch-1.0.0.dist-info/METADATA
niyofetch-1.0.0.dist-info/WHEEL
niyofetch-1.0.0.dist-info/entry_points.txt
niyofetch-1.0.0.dist-info/top_level.txt
niyofetch-1.0.0.dist-info/RECORD
