Metadata-Version: 2.1
Name: niyofetch
Version: 1.0.0
Summary: Embrace the GigaChad within you - Show off your system stats like a pro.
Home-page: https://github.com/r4mbhardwaj/niyofetch
Author: r4mbhardwaj
Author-email: r4mbhardwaj@gmail.com
License: MIT
Classifier: License :: OSI Approved :: MIT License
Classifier: Programming Language :: Python :: 3
Classifier: Programming Language :: Python :: 3.7
Classifier: Programming Language :: Python :: 3.8
Classifier: Programming Language :: Python :: 3.9
License-File: LICENSE.md
